LICENSE.txt
MANIFEST.in
README.md
setup.py
/usr/local/jenkins/workspace/mapr-kafka-python-2.6.0-release/opensource/mapr-kafka-python-2.6.0/LICENSE.txt
/usr/local/jenkins/workspace/mapr-kafka-python-2.6.0-release/opensource/mapr-kafka-python-2.6.0/src/confluent_kafka/src/Admin.c
/usr/local/jenkins/workspace/mapr-kafka-python-2.6.0-release/opensource/mapr-kafka-python-2.6.0/src/confluent_kafka/src/AdminTypes.c
/usr/local/jenkins/workspace/mapr-kafka-python-2.6.0-release/opensource/mapr-kafka-python-2.6.0/src/confluent_kafka/src/Consumer.c
/usr/local/jenkins/workspace/mapr-kafka-python-2.6.0-release/opensource/mapr-kafka-python-2.6.0/src/confluent_kafka/src/Metadata.c
/usr/local/jenkins/workspace/mapr-kafka-python-2.6.0-release/opensource/mapr-kafka-python-2.6.0/src/confluent_kafka/src/Producer.c
/usr/local/jenkins/workspace/mapr-kafka-python-2.6.0-release/opensource/mapr-kafka-python-2.6.0/src/confluent_kafka/src/confluent_kafka.c
src/confluent_kafka/__init__.py
src/confluent_kafka/deserializing_consumer.py
src/confluent_kafka/error.py
src/confluent_kafka/serializing_producer.py
src/confluent_kafka/_model/__init__.py
src/confluent_kafka/_util/__init__.py
src/confluent_kafka/_util/conversion_util.py
src/confluent_kafka/_util/validation_util.py
src/confluent_kafka/admin/__init__.py
src/confluent_kafka/admin/_acl.py
src/confluent_kafka/admin/_cluster.py
src/confluent_kafka/admin/_config.py
src/confluent_kafka/admin/_group.py
src/confluent_kafka/admin/_listoffsets.py
src/confluent_kafka/admin/_metadata.py
src/confluent_kafka/admin/_records.py
src/confluent_kafka/admin/_resource.py
src/confluent_kafka/admin/_scram.py
src/confluent_kafka/admin/_topic.py
src/confluent_kafka/auth_utils/__init__.py
src/confluent_kafka/auth_utils/mapr_auth_utils.py
src/confluent_kafka/avro/__init__.py
src/confluent_kafka/avro/cached_schema_registry_client.py
src/confluent_kafka/avro/error.py
src/confluent_kafka/avro/load.py
src/confluent_kafka/avro/serializer/__init__.py
src/mapr_streams_python.egg-info/PKG-INFO
src/mapr_streams_python.egg-info/SOURCES.txt
src/mapr_streams_python.egg-info/dependency_links.txt
src/mapr_streams_python.egg-info/requires.txt
src/mapr_streams_python.egg-info/top_level.txt