Metadata-Version: 2.1
Name: mapr-streams-python
Version: 2.6.0
Summary: Python client for Data Fabric Streams
Home-page: https://github.com/mapr/private-confluent-kafka-python
Author: Hewlett Packard Enterprise, Confluent Inc.
License: Apache License 2.0
Classifier: Development Status :: 5 - Production/Stable
Classifier: Intended Audience :: Developers
Classifier: License :: OSI Approved :: Apache Software License
Classifier: Programming Language :: Python
Classifier: Programming Language :: Python :: 2.7
Classifier: Programming Language :: Python :: 3
Classifier: Topic :: Software Development :: Libraries :: Python Modules
Provides-Extra: schema-registry
Provides-Extra: avro
Provides-Extra: json
Provides-Extra: protobuf
Provides-Extra: dev
Provides-Extra: doc
License-File: LICENSE.txt
